nnv/__init__.py
nnv/nnv.py
nnv-0.0.5.dist-info/LICENSE
nnv-0.0.5.dist-info/METADATA
nnv-0.0.5.dist-info/WHEEL
nnv-0.0.5.dist-info/top_level.txt
nnv-0.0.5.dist-info/RECORD
