Metadata-Version: 2.1
Name: nnv
Version: 0.0.5
Summary: A simple and easy to use tool to visualize Neural Networks.
Home-page: https://github.com/renatosc/nnv
Author: Renato Cordeiro
Author-email: opensource@renatocordeiro.com
License: UNKNOWN
Platform: UNKNOWN
Classifier: Programming Language :: Python :: 2.7
Classifier: License :: OSI Approved :: MIT License
Classifier: Operating System :: OS Independent
License-File: LICENSE
